README.md
setup.cfg
setup.py
get_html/__init__.py
get_html/__main__.py
get_html/_default.py
get_html/env_defined_get.py
get_html/html_renderer.py
get_html.egg-info/PKG-INFO
get_html.egg-info/SOURCES.txt
get_html.egg-info/dependency_links.txt
get_html.egg-info/requires.txt
get_html.egg-info/top_level.txt
tests/__init__.py
tests/test_contextmanager.py
tests/test_env_defined.py
tests/test_renderer.py