Metadata-Version: 2.1
Name: get-html
Version: 0.0.3
Summary: HTTP GET with JS rendering support, to get the rendered HTML from a page easily
Home-page: https://github.com/derlin/get-html
Author: Lucy Linder
Author-email: lucy.derlin@gmail.com
License: Apache License 2.0
Platform: UNKNOWN
Classifier: Programming Language :: Python :: 3
Classifier: License :: OSI Approved :: Apache Software License
Classifier: Operating System :: OS Independent
Requires-Python: >=3.6
